[
  {
    "componentname": "Action",
    "events": [
      "onerror",
      "onsuccess"
    ],
    "filename": "Action.info"
  },
  {
    "componentname": "ActionEventInfo",
    "events": [],
    "filename": "ActionEventInfo.info"
  },
  {
    "componentname": "AbstractComponent",
    "events": [
      "onclick",
      "oncontextmenu",
      "ondblclick",
      "ondrag",
      "ondragenter",
      "ondragleave",
      "ondragmove",
      "ondrop",
      "oninput",
      "onkeydown",
      "onkeyup",
      "onkillfocus",
      "onlbuttondown",
      "onlbuttonup",
      "onmousedown",
      "onmouseenter",
      "onmouseleave",
      "onmousemove",
      "onmouseup",
      "onmousewheel",
      "onmove",
      "onrbuttondown",
      "onrbuttonup",
      "onsetfocus",
      "onsize",
      "ontouchend",
      "ontouchmove",
      "ontouchstart"
    ],
    "filename": "AbstractComponent.info"
  },
  {
    "componentname": "ActivateEventInfo",
    "events": [],
    "filename": "ActivateEventInfo.info"
  },
  {
    "componentname": "AnimationEventInfo",
    "events": [],
    "filename": "AnimationEventInfo.info"
  },
  {
    "componentname": "Animation",
    "events": [
      "onbegin",
      "oncomplete",
      "onrun",
      "onupdate"
    ],
    "filename": "Animation.info"
  },
  {
    "componentname": "AbstractSelectAny",
    "events": [
      "canitemchange",
      "onclick",
      "oncontextmenu",
      "ondblclick",
      "ondevicebuttonup",
      "ondrag",
      "ondragenter",
      "ondragleave",
      "ondragmove",
      "ondrop",
      "oninnerdatachanged",
      "onitemchanged",
      "onitemclick",
      "onkeydown",
      "onkeyup",
      "onkillfocus",
      "onlbuttondown",
      "onlbuttonup",
      "onmousedown",
      "onmouseenter",
      "onmouseleave",
      "onmousemove",
      "onmove",
      "onrbuttondown",
      "onrbuttonup",
      "onsetfocus",
      "onsize",
      "ontouchend",
      "ontouchmove",
      "ontouchstart"
    ],
    "filename": "AbstractSelectAny.info"
  },
  {
    "componentname": "AnimationTimelineItem",
    "events": [],
    "filename": "AnimationTimelineItem.info"
  },
  {
    "componentname": "AnimationItem",
    "events": [],
    "filename": "AnimationItem.info"
  },
  {
    "componentname": "AbstractSelectOne",
    "events": [
      "canitemchange",
      "onclick",
      "oncontextmenu",
      "ondblclick",
      "ondevicebuttonup",
      "ondrag",
      "ondragenter",
      "ondragleave",
      "ondragmove",
      "ondrop",
      "oninnerdatachanged",
      "onitemchanged",
      "onitemclick",
      "onkeydown",
      "onkeyup",
      "onkillfocus",
      "onlbuttondown",
      "onlbuttonup",
      "onmousedown",
      "onmouseenter",
      "onmouseleave",
      "onmousemove",
      "onmove",
      "onrbuttondown",
      "onrbuttonup",
      "onsetfocus",
      "onsize",
      "ontouchend",
      "ontouchmove",
      "ontouchstart"
    ],
    "filename": "AbstractSelectOne.info"
  },
  {
    "componentname": "AnimationTimeline",
    "events": [
      "onbegin",
      "oncomplete",
      "onrun",
      "onupdate"
    ],
    "filename": "AnimationTimeline.info"
  },
  {
    "componentname": "BindItem",
    "events": [],
    "filename": "BindItem.info"
  },
  {
    "componentname": "BindingValueChangedEventInfo",
    "events": [],
    "filename": "BindingValueChangedEventInfo.info"
  },
  {
    "componentname": "CalendarCloseUpEventInfo",
    "events": [],
    "filename": "CalendarCloseUpEventInfo.info"
  },
  {
    "componentname": "CalendarDayClickEventInfo",
    "events": [],
    "filename": "CalendarDayClickEventInfo.info"
  },
  {
    "componentname": "CalendarSpinEventInfo",
    "events": [],
    "filename": "CalendarSpinEventInfo.info"
  },
  {
    "componentname": "Button",
    "events": [
      "onclick",
      "oncontextmenu",
      "ondblclick",
      "ondevicebuttonup",
      "ondrag",
      "ondragenter",
      "ondragleave",
      "ondragmove",
      "ondrop",
      "oninput",
      "onkeydown",
      "onkeyup",
      "onkillfocus",
      "onlbuttondown",
      "onlbuttonup",
      "onmousedown",
      "onmouseenter",
      "onmouseleave",
      "onmousemove",
      "onmouseup",
      "onmousewheel",
      "onmove",
      "onrbuttondown",
      "onrbuttonup",
      "onsetfocus",
      "onsize",
      "ontouchend",
      "ontouchmove",
      "ontouchstart"
    ],
    "filename": "Button.info"
  },
  {
    "componentname": "CellRowGroupControl",
    "events": [
      "onclick",
      "oncontextmenu",
      "ondblclick",
      "ondrag",
      "ondragenter",
      "ondragleave",
      "ondragmove",
      "ondrop",
      "oninput",
      "onkeydown",
      "onkeyup",
      "onkillfocus",
      "onlbuttondown",
      "onlbuttonup",
      "onmousedown",
      "onmouseenter",
      "onmouseleave",
      "onmousemove",
      "onmouseup",
      "onmousewheel",
      "onmove",
      "onrbuttondown",
      "onrbuttonup",
      "onsetfocus",
      "onsize",
      "ontouchend",
      "ontouchmove",
      "ontouchstart"
    ],
    "filename": "CellRowGroupControl.info"
  },
  {
    "componentname": "ChangeEventInfo",
    "events": [],
    "filename": "ChangeEventInfo.info"
  },
  {
    "componentname": "CellTreeLineControl",
    "events": [],
    "filename": "CellTreeLineControl.info"
  },
  {
    "componentname": "CheckBoxChangedEventInfo",
    "events": [],
    "filename": "CheckBoxChangedEventInfo.info"
  },
  {
    "componentname": "CellTreeItemControl",
    "events": [
      "onclick",
      "oncontextmenu",
      "ondblclick",
      "ondrag",
      "ondragenter",
      "ondragleave",
      "ondragmove",
      "ondrop",
      "oninput",
      "onkeydown",
      "onkeyup",
      "onkillfocus",
      "onlbuttondown",
      "onlbuttonup",
      "onmousedown",
      "onmouseenter",
      "onmouseleave",
      "onmousemove",
      "onmouseup",
      "onmousewheel",
      "onmove",
      "onrbuttondown",
      "onrbuttonup",
      "onsetfocus",
      "onsize",
      "ontouchend",
      "ontouchmove",
      "ontouchstart"
    ],
    "filename": "CellTreeItemControl.info"
  },
  {
    "componentname": "Calendar",
    "events": [
      "canchange",
      "onchanged",
      "onclick",
      "oncloseup",
      "oncontextmenu",
      "ondayclick",
      "ondblclick",
      "ondevicebuttonup",
      "ondrag",
      "ondragenter",
      "ondragleave",
      "ondragmove",
      "ondrop",
      "ondropdown",
      "oneditclick",
      "oninnerdatachanged",
      "oninput",
      "onkeydown",
      "onkeyup",
      "onkillfocus",
      "onlbuttondown",
      "onlbuttonup",
      "onmousedown",
      "onmouseenter",
      "onmouseleave",
      "onmousemove",
      "onmouseup",
      "onmousewheel",
      "onmove",
      "onrbuttondown",
      "onrbuttonup",
      "onsetfocus",
      "onsize",
      "onspin",
      "ontouchend",
      "ontouchmove",
      "ontouchstart"
    ],
    "filename": "Calendar.info"
  },
  {
    "componentname": "ClickEventInfo",
    "events": [],
    "filename": "ClickEventInfo.info"
  },
  {
    "componentname": "CloseEventInfo",
    "events": [],
    "filename": "CloseEventInfo.info"
  },
  {
    "componentname": "ColumnInfo",
    "events": [],
    "filename": "ColumnInfo.info"
  },
  {
    "componentname": "CheckBoxSet",
    "events": [
      "canitemchange",
      "onclick",
      "oncontextmenu",
      "ondblclick",
      "ondevicebuttonup",
      "ondrag",
      "ondragenter",
      "ondragleave",
      "ondragmove",
      "ondrop",
      "onhscroll",
      "oninnerdatachanged",
      "oninput",
      "onitemchanged",
      "onitemclick",
      "onkeydown",
      "onkeyup",
      "onkillfocus",
      "onlbuttondown",
      "onlbuttonup",
      "onmousedown",
      "onmouseenter",
      "onmouseleave",
      "onmousemove",
      "onmouseup",
      "onmousewheel",
      "onmove",
      "onrbuttondown",
      "onrbuttonup",
      "onsetfocus",
      "onsize",
      "ontouchend",
      "ontouchmove",
      "ontouchstart"
    ],
    "filename": "CheckBoxSet.info"
  },
  {
    "componentname": "ComboCloseUpEventInfo",
    "events": [],
    "filename": "ComboCloseUpEventInfo.info"
  },
  {
    "componentname": "CheckBox",
    "events": [
      "canchange",
      "onchanged",
      "onclick",
      "oncontextmenu",
      "ondblclick",
      "ondevicebuttonup",
      "ondrag",
      "ondragenter",
      "ondragleave",
      "ondragmove",
      "ondrop",
      "oninput",
      "onkeydown",
      "onkeyup",
      "onkillfocus",
      "onlbuttondown",
      "onlbuttonup",
      "onmousedown",
      "onmouseenter",
      "onmouseleave",
      "onmousemove",
      "onmouseup",
      "onmousewheel",
      "onmove",
      "onrbuttondown",
      "onrbuttonup",
      "onsetfocus",
      "onsize",
      "ontouchend",
      "ontouchmove",
      "ontouchstart"
    ],
    "filename": "CheckBox.info"
  },
  {
    "componentname": "ChildFrame",
    "events": [
      "onactivate",
      "onbeforeclose",
      "onclick",
      "onclose",
      "oncontextmenu",
      "ondblclick",
      "ondeactivate",
      "ondrag",
      "ondragenter",
      "ondragleave",
      "ondragmove",
      "ondrop",
      "oninput",
      "onkeydown",
      "onkeyup",
      "onkillfocus",
      "onlbuttondown",
      "onlbuttonup",
      "onmousedown",
      "onmouseenter",
      "onmouseleave",
      "onmousemove",
      "onmouseup",
      "onmousewheel",
      "onmove",
      "onorientationchange",
      "onrootcssclasschange",
      "onrbuttondown",
      "onrbuttonup",
      "onsetfocus",
      "onsize",
      "onsyscommand",
      "ontouchend",
      "ontouchmove",
      "ontouchstart"
    ],
    "filename": "ChildFrame.info"
  },
  {
    "componentname": "ContentErrorEventInfo",
    "events": [],
    "filename": "ContentErrorEventInfo.info"
  },
  {
    "componentname": "ContentLoadEventInfo",
    "events": [],
    "filename": "ContentLoadEventInfo.info"
  },
  {
    "componentname": "Combo",
    "events": [
      "canitemchange",
      "onclick",
      "oncloseup",
      "oncontextmenu",
      "ondblclick",
      "ondevicebuttonup",
      "ondrag",
      "ondragenter",
      "ondragleave",
      "ondragmove",
      "ondrop",
      "ondropdown",
      "oneditclick",
      "oninnerdatachanged",
      "oninput",
      "onitemchanged",
      "onitemclick",
      "onkeydown",
      "onkeyup",
      "onkillfocus",
      "onlbuttondown",
      "onlbuttonup",
      "onmousedown",
      "onmouseenter",
      "onmouseleave",
      "onmousemove",
      "onmouseup",
      "onmousewheel",
      "onmove",
      "onrbuttondown",
      "onrbuttonup",
      "onsetfocus",
      "onsize",
      "ontouchend",
      "ontouchmove",
      "ontouchstart"
    ],
    "filename": "Combo.info"
  },
  {
    "componentname": "Component",
    "events": [
      "onclick",
      "oncontextmenu",
      "ondblclick",
      "ondrag",
      "ondragenter",
      "ondragleave",
      "ondragmove",
      "ondrop",
      "oninput",
      "onkeydown",
      "onkeyup",
      "onkillfocus",
      "onlbuttondown",
      "onlbuttonup",
      "onmousedown",
      "onmouseenter",
      "onmouseleave",
      "onmousemove",
      "onmouseup",
      "onmousewheel",
      "onmove",
      "onrbuttondown",
      "onrbuttonup",
      "onsetfocus",
      "onsize",
      "ontouchend",
      "ontouchmove",
      "ontouchstart"
    ],
    "filename": "Component.info"
  },
  {
    "componentname": "DataObject",
    "events": [
      "ondatachanged",
      "onerror",
      "onload",
      "onloaddatasets",
      "onsuccess",
      "onvaluechanged"
    ],
    "filename": "DataObject.info"
  },
  {
    "componentname": "ContextMenuEventInfo",
    "events": [],
    "filename": "ContextMenuEventInfo.info"
  },
  {
    "componentname": "DataObjectDataChangedEventInfo",
    "events": [],
    "filename": "DataObjectDataChangedEventInfo.info"
  },
  {
    "componentname": "DataObjectErrorEventInfo",
    "events": [],
    "filename": "DataObjectErrorEventInfo.info"
  },
  {
    "componentname": "DataObjectEventInfo",
    "events": [],
    "filename": "DataObjectEventInfo.info"
  },
  {
    "componentname": "DataObjectLoadDatasetsEventInfo",
    "events": [],
    "filename": "DataObjectLoadDatasetsEventInfo.info"
  },
  {
    "componentname": "DataObjectLoadEventInfo",
    "events": [],
    "filename": "DataObjectLoadEventInfo.info"
  },
  {
    "componentname": "CompositeComponent",
    "events": [
      "onclick",
      "oncontextmenu",
      "ondblclick",
      "ondrag",
      "ondragenter",
      "ondragleave",
      "ondragmove",
      "ondrop",
      "onhscroll",
      "oninput",
      "onkeydown",
      "onkeyup",
      "onkillfocus",
      "onlbuttondown",
      "onlbuttonup",
      "onmousedown",
      "onmouseenter",
      "onmouseleave",
      "onmousemove",
      "onmouseup",
      "onmousewheel",
      "onmove",
      "onrbuttondown",
      "onrbuttonup",
      "onsetfocus",
      "onsize",
      "ontouchend",
      "ontouchmove",
      "ontouchstart",
      "onvscroll"
    ],
    "filename": "CompositeComponent.info"
  },
  {
    "componentname": "DataObjectValueChangedEventInfo",
    "events": [],
    "filename": "DataObjectValueChangedEventInfo.info"
  },
  {
    "componentname": "DateFieldDayClickEventInfo",
    "events": [],
    "filename": "DateFieldDayClickEventInfo.info"
  },
  {
    "componentname": "DateFieldCloseUpEventInfo",
    "events": [],
    "filename": "DateFieldCloseUpEventInfo.info"
  },
  {
    "componentname": "DatePickerBodyControl",
    "events": [],
    "filename": "DatePickerBodyControl.info"
  },
  {
    "componentname": "DateFieldBoxControl",
    "events": [
      "onclick",
      "oncontextmenu",
      "ondblclick",
      "ondrag",
      "ondragenter",
      "ondragleave",
      "ondragmove",
      "ondrop",
      "oninput",
      "onkeydown",
      "onkeyup",
      "onkillfocus",
      "onlbuttondown",
      "onlbuttonup",
      "onmousedown",
      "onmouseenter",
      "onmouseleave",
      "onmousemove",
      "onmouseup",
      "onmousewheel",
      "onmove",
      "onrbuttondown",
      "onrbuttonup",
      "onsetfocus",
      "onsize",
      "ontouchend",
      "ontouchmove",
      "ontouchstart"
    ],
    "filename": "DateFieldBoxControl.info"
  },
  {
    "componentname": "DatePickerControl",
    "events": [],
    "filename": "DatePickerControl.info"
  },
  {
    "componentname": "DatePickerDayItemControl",
    "events": [],
    "filename": "DatePickerDayItemControl.info"
  },
  {
    "componentname": "DatePickerHeadControl",
    "events": [],
    "filename": "DatePickerHeadControl.info"
  },
  {
    "componentname": "DatePickerGroupControl",
    "events": [
      "onclick",
      "oncontextmenu",
      "ondblclick",
      "ondrag",
      "ondragenter",
      "ondragleave",
      "ondragmove",
      "ondrop",
      "oninput",
      "onkeydown",
      "onkeyup",
      "onkillfocus",
      "onlbuttondown",
      "onlbuttonup",
      "onmousedown",
      "onmouseenter",
      "onmouseleave",
      "onmousemove",
      "onmouseup",
      "onmousewheel",
      "onmove",
      "onrbuttondown",
      "onrbuttonup",
      "onsetfocus",
      "onsize",
      "ontouchend",
      "ontouchmove",
      "ontouchstart"
    ],
    "filename": "DatePickerGroupControl.info"
  },
  {
    "componentname": "DateField",
    "events": [
      "canchange",
      "onchanged",
      "onclick",
      "oncloseup",
      "oncontextmenu",
      "ondayclick",
      "ondblclick",
      "ondevicebuttonup",
      "ondrag",
      "ondragenter",
      "ondragleave",
      "ondragmove",
      "ondrop",
      "ondropdown",
      "oneditclick",
      "oninnerdatachanged",
      "oninput",
      "oninvalid",
      "onkeydown",
      "onkeyup",
      "onkillfocus",
      "onlbuttondown",
      "onlbuttonup",
      "onmousedown",
      "onmouseenter",
      "onmouseleave",
      "onmousemove",
      "onmouseup",
      "onmousewheel",
      "onmove",
      "onrbuttondown",
      "onrbuttonup",
      "onsetfocus",
      "onsize",
      "onspin",
      "ontouchend",
      "ontouchmove",
      "ontouchstart"
    ],
    "filename": "DateField.info"
  },
  {
    "componentname": "DatePickerYearItemControl",
    "events": [
      "onclick",
      "oncontextmenu",
      "ondblclick",
      "ondrag",
      "ondragenter",
      "ondragleave",
      "ondragmove",
      "ondrop",
      "oninput",
      "onkeydown",
      "onkeyup",
      "onkillfocus",
      "onlbuttondown",
      "onlbuttonup",
      "onmousedown",
      "onmouseenter",
      "onmouseleave",
      "onmousemove",
      "onmouseup",
      "onmousewheel",
      "onmove",
      "onrbuttondown",
      "onrbuttonup",
      "onsetfocus",
      "onsize",
      "ontouchend",
      "ontouchmove",
      "ontouchstart"
    ],
    "filename": "DatePickerYearItemControl.info"
  },
  {
    "componentname": "DatePickerWeekItemControl",
    "events": [],
    "filename": "DatePickerWeekItemControl.info"
  },
  {
    "componentname": "Dataset",
    "events": [
      "cancolumnchange",
      "canrowposchange",
      "oncolumnchanged",
      "onload",
      "onrowposchanged",
      "onrowsetchanged",
      "onvaluechanged"
    ],
    "filename": "Dataset.info"
  },
  {
    "componentname": "DateRangePickerDayClickEventInfo",
    "events": [],
    "filename": "DateRangePickerDayClickEventInfo.info"
  },
  {
    "componentname": "DeviceButtonEventInfo",
    "events": [],
    "filename": "DeviceButtonEventInfo.info"
  },
  {
    "componentname": "DragEventInfo",
    "events": [],
    "filename": "DragEventInfo.info"
  },
  {
    "componentname": "DSColChangeEventInfo",
    "events": [],
    "filename": "DSColChangeEventInfo.info"
  },
  {
    "componentname": "DSLoadEventInfo",
    "events": [],
    "filename": "DSLoadEventInfo.info"
  },
  {
    "componentname": "DSRowsetChangeEventInfo",
    "events": [],
    "filename": "DSRowsetChangeEventInfo.info"
  },
  {
    "componentname": "DSRowPosChangeEventInfo",
    "events": [],
    "filename": "DSRowPosChangeEventInfo.info"
  },
  {
    "componentname": "DateRangePicker",
    "events": [
      "onchanged",
      "onclick",
      "oncontextmenu",
      "ondayclick",
      "ondblclick",
      "ondevicebuttonup",
      "ondrag",
      "ondragenter",
      "ondragleave",
      "ondragmove",
      "ondrop",
      "oninnerdatachanged",
      "oninput",
      "onkeydown",
      "onkeyup",
      "onkillfocus",
      "onlbuttondown",
      "onlbuttonup",
      "onmousedown",
      "onmouseenter",
      "onmouseleave",
      "onmousemove",
      "onmouseup",
      "onmousewheel",
      "onmove",
      "onrbuttondown",
      "onrbuttonup",
      "onsetfocus",
      "onsize",
      "ontouchend",
      "ontouchmove",
      "ontouchstart"
    ],
    "filename": "DateRangePicker.info"
  },
  {
    "componentname": "EditClickEventInfo",
    "events": [],
    "filename": "EditClickEventInfo.info"
  },
  {
    "componentname": "EventInfo",
    "events": [],
    "filename": "EventInfo.info"
  },
  {
    "componentname": "EnableStatusChangedEventInfo",
    "events": [],
    "filename": "EnableStatusChangedEventInfo.info"
  },
  {
    "componentname": "ExcelExportEventInfo",
    "events": [],
    "filename": "ExcelExportEventInfo.info"
  },
  {
    "componentname": "Div",
    "events": [
      "onclick",
      "oncontextmenu",
      "ondblclick",
      "ondevicebuttonup",
      "ondrag",
      "ondragenter",
      "ondragleave",
      "ondragmove",
      "ondrop",
      "onhscroll",
      "oninput",
      "onkeydown",
      "onkeyup",
      "onkillfocus",
      "onlbuttondown",
      "onlbuttonup",
      "onmousedown",
      "onmouseenter",
      "onmouseleave",
      "onmousemove",
      "onmouseup",
      "onmousewheel",
      "onmove",
      "onrbuttondown",
      "onrbuttonup",
      "onsetfocus",
      "onsize",
      "ontouchend",
      "ontouchmove",
      "ontouchstart",
      "onvscroll"
    ],
    "filename": "Div.info"
  },
  {
    "componentname": "ExcelExportErrorEventInfo",
    "events": [],
    "filename": "ExcelExportErrorEventInfo.info"
  },
  {
    "componentname": "ExcelImportErrorEventInfo",
    "events": [],
    "filename": "ExcelImportErrorEventInfo.info"
  },
  {
    "componentname": "ExcelExportProgressEventInfo",
    "events": [],
    "filename": "ExcelExportProgressEventInfo.info"
  },
  {
    "componentname": "Edit",
    "events": [
      "canchange",
      "onchanged",
      "onclick",
      "oncontextmenu",
      "ondblclick",
      "ondevicebuttonup",
      "ondrag",
      "ondragenter",
      "ondragleave",
      "ondragmove",
      "ondrop",
      "oneditclick",
      "onimeaction",
      "oninput",
      "onkeydown",
      "onkeyup",
      "onkillfocus",
      "onlbuttondown",
      "onlbuttonup",
      "onmousedown",
      "onmouseenter",
      "onmouseleave",
      "onmousemove",
      "onmouseup",
      "onmousewheel",
      "onmove",
      "onrbuttondown",
      "onrbuttonup",
      "onsetfocus",
      "onsize",
      "ontouchend",
      "ontouchmove",
      "ontouchstart"
    ],
    "filename": "Edit.info"
  },
  {
    "componentname": "ExportItemTypes",
    "events": [],
    "filename": "ExportItemTypes.info"
  },
  {
    "componentname": "ExcelImportEventInfo",
    "events": [],
    "filename": "ExcelImportEventInfo.info"
  },
  {
    "componentname": "ExcelExportObject",
    "events": [
      "onerror",
      "onprogress",
      "onsuccess"
    ],
    "filename": "ExcelExportObject.info"
  },
  {
    "componentname": "ExportProgressControl",
    "events": [],
    "filename": "ExportProgress.info"
  },
  {
    "componentname": "ExportItem",
    "events": [],
    "filename": "ExportItem.info"
  },
  {
    "componentname": "ExtendedCommandEventInfo",
    "events": [],
    "filename": "ExtendedCommandEventInfo.info"
  },
  {
    "componentname": "ExportTypes",
    "events": [],
    "filename": "ExportTypes.info"
  },
  {
    "componentname": "ExcelImportObject",
    "events": [
      "onerror",
      "onsuccess"
    ],
    "filename": "ExcelImportObject.info"
  },
  {
    "componentname": "FileDialog",
    "events": [
      "onclose"
    ],
    "filename": "FileDialog.info"
  },
  {
    "componentname": "FileDialogEventInfo",
    "events": [],
    "filename": "FileDialogEventInfo.info"
  },
  {
    "componentname": "FileDownloadErrorEventInfo",
    "events": [],
    "filename": "FileDownloadErrorEventInfo.info"
  },
  {
    "componentname": "FieldBaseIconControl",
    "events": [
      "onclick",
      "oncontextmenu",
      "ondblclick",
      "ondrag",
      "ondragenter",
      "ondragleave",
      "ondragmove",
      "ondrop",
      "oninput",
      "onkeydown",
      "onkeyup",
      "onkillfocus",
      "onlbuttondown",
      "onlbuttonup",
      "onmousedown",
      "onmouseenter",
      "onmouseleave",
      "onmousemove",
      "onmouseup",
      "onmousewheel",
      "onmove",
      "onrbuttondown",
      "onrbuttonup",
      "onsetfocus",
      "onsize",
      "ontouchend",
      "ontouchmove",
      "ontouchstart"
    ],
    "filename": "FieldBaseIconControl.info"
  },
  {
    "componentname": "FieldBaseLabelControl",
    "events": [
      "onclick",
      "oncontextmenu",
      "ondblclick",
      "ondrag",
      "ondragenter",
      "ondragleave",
      "ondragmove",
      "ondrop",
      "oninput",
      "onkeydown",
      "onkeyup",
      "onkillfocus",
      "onlbuttondown",
      "onlbuttonup",
      "onmousedown",
      "onmouseenter",
      "onmouseleave",
      "onmousemove",
      "onmouseup",
      "onmousewheel",
      "onmove",
      "onrbuttondown",
      "onrbuttonup",
      "onsetfocus",
      "onsize",
      "ontouchend",
      "ontouchmove",
      "ontouchstart"
    ],
    "filename": "FieldBaseLabelControl.info"
  },
  {
    "componentname": "FieldBaseTextControl",
    "events": [
      "onclick",
      "oncontextmenu",
      "ondblclick",
      "ondrag",
      "ondragenter",
      "ondragleave",
      "ondragmove",
      "ondrop",
      "oninput",
      "onkeydown",
      "onkeyup",
      "onkillfocus",
      "onlbuttondown",
      "onlbuttonup",
      "onmousedown",
      "onmouseenter",
      "onmouseleave",
      "onmousemove",
      "onmouseup",
      "onmousewheel",
      "onmove",
      "onrbuttondown",
      "onrbuttonup",
      "onsetfocus",
      "onsize",
      "ontouchend",
      "ontouchmove",
      "ontouchstart"
    ],
    "filename": "FieldBaseTextControl.info"
  },
  {
    "componentname": "FileDownloadEventInfo",
    "events": [],
    "filename": "FileDownloadEventInfo.info"
  },
  {
    "componentname": "FileDownTransferErrorEventInfo",
    "events": [],
    "filename": "FileDownTransferErrorEventInfo.info"
  },
  {
    "componentname": "FileDownTransferEventInfo",
    "events": [],
    "filename": "FileDownTransferEventInfo.info"
  },
  {
    "componentname": "FileDownTransfer",
    "events": [
      "onerror",
      "onsuccess"
    ],
    "filename": "FileDownTransfer.info"
  },
  {
    "componentname": "FileUploadContextMenuEventInfo",
    "events": [],
    "filename": "FileUploadContextMenuEventInfo.info"
  },
  {
    "componentname": "FileUploadErrorEventInfo",
    "events": [],
    "filename": "FileUploadErrorEventInfo.info"
  },
  {
    "componentname": "FileUploadItemChangeEventInfo",
    "events": [],
    "filename": "FileUploadItemChangeEventInfo.info"
  },
  {
    "componentname": "FileUploadEventInfo",
    "events": [],
    "filename": "FileUploadEventInfo.info"
  },
  {
    "componentname": "FileUploadItemEventInfo",
    "events": [],
    "filename": "FileUploadItemEventInfo.info"
  },
  {
    "componentname": "FileUploadMouseEventInfo",
    "events": [],
    "filename": "FileUploadMouseEventInfo.info"
  },
  {
    "componentname": "FileDownload",
    "events": [
      "onclick",
      "oncontextmenu",
      "ondblclick",
      "ondevicebuttonup",
      "ondrag",
      "ondragenter",
      "ondragleave",
      "ondragmove",
      "ondrop",
      "onerror",
      "oninput",
      "onkeydown",
      "onkeyup",
      "onkillfocus",
      "onlbuttondown",
      "onlbuttonup",
      "onmousedown",
      "onmouseenter",
      "onmouseleave",
      "onmousemove",
      "onmouseup",
      "onmousewheel",
      "onmove",
      "onrbuttondown",
      "onrbuttonup",
      "onsetfocus",
      "onsize",
      "onsuccess",
      "ontouchend",
      "ontouchmove",
      "ontouchstart"
    ],
    "filename": "FileDownload.info"
  },
  {
    "componentname": "FileUpTransfer",
    "events": [
      "onerror",
      "onprogress",
      "onsuccess"
    ],
    "filename": "FileUpTransfer.info"
  },
  {
    "componentname": "FileUpTransferEventInfo",
    "events": [],
    "filename": "FileUpTransferEventInfo.info"
  },
  {
    "componentname": "FileUploadItemControl",
    "events": [
      "onclick",
      "oncontextmenu",
      "ondblclick",
      "ondrag",
      "ondragenter",
      "ondragleave",
      "ondragmove",
      "ondrop",
      "oninput",
      "onkeydown",
      "onkeyup",
      "onkillfocus",
      "onlbuttondown",
      "onlbuttonup",
      "onmousedown",
      "onmouseenter",
      "onmouseleave",
      "onmousemove",
      "onmouseup",
      "onmousewheel",
      "onmove",
      "onrbuttondown",
      "onrbuttonup",
      "onsetfocus",
      "onsize",
      "ontouchend",
      "ontouchmove",
      "ontouchstart"
    ],
    "filename": "FileUploadItemControl.info"
  },
  {
    "componentname": "FileUpTransferErrorEventInfo",
    "events": [],
    "filename": "FileUpTransferErrorEventInfo.info"
  },
  {
    "componentname": "FileUpload",
    "events": [
      "onappenditem",
      "onclick",
      "oncontextmenu",
      "ondblclick",
      "ondeleteitem",
      "ondevicebuttonup",
      "ondrag",
      "ondragenter",
      "ondragleave",
      "ondragmove",
      "ondrop",
      "onerror",
      "onfindclick",
      "oninput",
      "onitemchanged",
      "onitemclick",
      "onkeydown",
      "onkeyup",
      "onkillfocus",
      "onlbuttondown",
      "onlbuttonup",
      "onmousedown",
      "onmouseenter",
      "onmouseleave",
      "onmousemove",
      "onmouseup",
      "onmousewheel",
      "onmove",
      "onrbuttondown",
      "onrbuttonup",
      "onsetfocus",
      "onsize",
      "onsuccess",
      "ontouchend",
      "ontouchmove",
      "ontouchstart"
    ],
    "filename": "FileUpload.info"
  },
  {
    "componentname": "FileUpTransferProgressEventInfo",
    "events": [],
    "filename": "FileUpTransferProgressEventInfo.info"
  },
  {
    "componentname": "FlexTextControl",
    "events": [
      "onclick",
      "oncontextmenu",
      "ondblclick",
      "ondrag",
      "ondragenter",
      "ondragleave",
      "ondragmove",
      "ondrop",
      "oninput",
      "onkeydown",
      "onkeyup",
      "onkillfocus",
      "onlbuttondown",
      "onlbuttonup",
      "onmousedown",
      "onmouseenter",
      "onmouseleave",
      "onmousemove",
      "onmouseup",
      "onmousewheel",
      "onmove",
      "onrbuttondown",
      "onrbuttonup",
      "onsetfocus",
      "onsize",
      "ontouchend",
      "ontouchmove",
      "ontouchstart"
    ],
    "filename": "FlexTextControl.info"
  },
  {
    "componentname": "GoogleMapCircle",
    "events": [],
    "filename": "GoogleMapCircle.info"
  },
  {
    "componentname": "GoogleMapDragEventInfo",
    "events": [],
    "filename": "GoogleMapDragEventInfo.info"
  },
  {
    "componentname": "GoogleMapMarker",
    "events": [],
    "filename": "GoogleMapMarker.info"
  },
  {
    "componentname": "GoogleMapClickEventInfo",
    "events": [],
    "filename": "GoogleMapClickEventInfo.info"
  },
  {
    "componentname": "GoogleMapErrorEventInfo",
    "events": [],
    "filename": "GoogleMapErrorEventInfo.info"
  },
  {
    "componentname": "GoogleMapEventInfo",
    "events": [],
    "filename": "GoogleMapEventInfo.info"
  },
  {
    "componentname": "GoogleMapPolygon",
    "events": [],
    "filename": "GoogleMapPolygon.info"
  },
  {
    "componentname": "GoogleMap",
    "events": [
      "onclick",
      "oncontextmenu",
      "ondblclick",
      "ondrag",
      "ondragenter",
      "ondragleave",
      "ondragmove",
      "ondrop",
      "onerror",
      "oninput",
      "onkeydown",
      "onkeyup",
      "onkillfocus",
      "onlbuttondown",
      "onlbuttonup",
      "onload",
      "onmapdrag",
      "onmapdragend",
      "onmapdragstart",
      "onmousedown",
      "onmouseenter",
      "onmouseleave",
      "onmousemove",
      "onmouseup",
      "onmousewheel",
      "onmove",
      "onrbuttondown",
      "onrbuttonup",
      "onrecvsuccess",
      "onsetfocus",
      "onsize",
      "ontouchend",
      "ontouchmove",
      "ontouchstart"
    ],
    "filename": "GoogleMap.info"
  },
  {
    "componentname": "FrameSet",
    "events": [
      "onactivate",
      "onbeforeclose",
      "onclick",
      "onclose",
      "oncontextmenu",
      "ondblclick",
      "ondeactivate",
      "ondrag",
      "ondragenter",
      "ondragleave",
      "ondragmove",
      "ondrop",
      "oninput",
      "onkeydown",
      "onkeyup",
      "onkillfocus",
      "onlbuttondown",
      "onlbuttonup",
      "onmousedown",
      "onmouseenter",
      "onmouseleave",
      "onmousemove",
      "onmouseup",
      "onmousewheel",
      "onmove",
      "onorientationchange",
      "onrootcssclasschange",
      "onrbuttondown",
      "onrbuttonup",
      "onsetfocus",
      "onsize",
      "onsyscommand",
      "ontouchend",
      "ontouchmove",
      "ontouchstart",
      "ontabbarextrabuttonclick",
      "ontabbarheadbuttonclick"
    ],
    "filename": "FrameSet.info"
  },
  {
    "componentname": "GoogleMapPolyline",
    "events": [],
    "filename": "GoogleMapPolyline.info"
  },
  {
    "componentname": "IconControl",
    "events": [
      "onclick",
      "oncontextmenu",
      "ondblclick",
      "ondrag",
      "ondragenter",
      "ondragleave",
      "ondragmove",
      "ondrop",
      "oninput",
      "onkeydown",
      "onkeyup",
      "onkillfocus",
      "onlbuttondown",
      "onlbuttonup",
      "onmousedown",
      "onmouseenter",
      "onmouseleave",
      "onmousemove",
      "onmouseup",
      "onmousewheel",
      "onmove",
      "onrbuttondown",
      "onrbuttonup",
      "onsetfocus",
      "onsize",
      "ontouchend",
      "ontouchmove",
      "ontouchstart"
    ],
    "filename": "IconControl.info"
  },
  {
    "componentname": "Form",
    "events": [
      "canlayoutchange",
      "canstepchange",
      "onactivate",
      "onbeforeclose",
      "onbindingvaluechanged",
      "onclick",
      "onclose",
      "oncontextmenu",
      "ondblclick",
      "ondeactivate",
      "ondevicebuttonup",
      "ondrag",
      "ondragenter",
      "ondragleave",
      "ondragmove",
      "ondrop",
      "onerror",
      "onextendedcommand",
      "onhscroll",
      "oninit",
      "oninput",
      "onkeydown",
      "onkeyup",
      "onkillfocus",
      "onlayoutchanged",
      "onlbuttondown",
      "onlbuttonup",
      "onload",
      "onmouseenter",
      "onmouseleave",
      "onmousemove",
      "onmousewheel",
      "onmove",
      "onorientationchange",
      "onrootcssclasschange",
      "onrbuttondown",
      "onrbuttonup",
      "onsetfocus",
      "onsize",
      "onstepchanged",
      "ontimer",
      "ontouchend",
      "ontouchmove",
      "ontouchstart",
      "onvscroll",
      "onfetchstatedata",
      "onrestorestatedata"
    ],
    "filename": "Form.info"
  },
  {
    "componentname": "HTMLContentBox",
    "events": [
      "onclick",
      "oncontextmenu",
      "ondevicebuttonup",
      "ondrag",
      "ondragenter",
      "ondragleave",
      "ondragmove",
      "ondrop",
      "onkeydown",
      "onkeyup",
      "onkillfocus",
      "onlbuttondown",
      "onlbuttonup",
      "onmousedown",
      "onmouseenter",
      "onmouseleave",
      "onmousemove",
      "onmouseup",
      "onmousewheel",
      "onmove",
      "onrbuttondown",
      "onrbuttonup",
      "onsetfocus",
      "onsize",
      "ontouchend",
      "ontouchmove",
      "ontouchstart",
      "oncontentloaded",
      "onvaluechanged",
      "onenablestatuschanged",
      "onerror"
    ],
    "filename": "HTMLContentBox.info"
  },
  {
    "componentname": "GroupBox",
    "events": [
      "onclick",
      "oncontextmenu",
      "ondblclick",
      "ondrag",
      "ondragenter",
      "ondragleave",
      "ondragmove",
      "ondrop",
      "oninput",
      "onkeydown",
      "onkeyup",
      "onkillfocus",
      "onlbuttondown",
      "onlbuttonup",
      "onmousedown",
      "onmouseenter",
      "onmouseleave",
      "onmousemove",
      "onmouseup",
      "onmousewheel",
      "onmove",
      "onrbuttondown",
      "onrbuttonup",
      "onsetfocus",
      "onsize",
      "ontouchend",
      "ontouchmove",
      "ontouchstart"
    ],
    "filename": "GroupBox.info"
  },
  {
    "componentname": "HFrameSet",
    "events": [
      "onactivate",
      "onbeforeclose",
      "onclick",
      "onclose",
      "oncontextmenu",
      "ondblclick",
      "ondeactivate",
      "ondrag",
      "ondragenter",
      "ondragleave",
      "ondragmove",
      "ondrop",
      "oninput",
      "onkeydown",
      "onkeyup",
      "onkillfocus",
      "onlbuttondown",
      "onlbuttonup",
      "onmousedown",
      "onmouseenter",
      "onmouseleave",
      "onmousemove",
      "onmouseup",
      "onmousewheel",
      "onmove",
      "onorientationchange",
      "onrootcssclasschange",
      "onrbuttondown",
      "onrbuttonup",
      "onsetfocus",
      "onsize",
      "onsyscommand",
      "ontouchend",
      "ontouchmove",
      "ontouchstart"
    ],
    "filename": "HFrameSet.info"
  },
  {
    "componentname": "ImportTypes",
    "events": [],
    "filename": "ImportTypes.info"
  },
  {
    "componentname": "ImageAreaControl",
    "events": [
      "onclick",
      "oncontextmenu",
      "ondblclick",
      "ondrag",
      "ondragenter",
      "ondragleave",
      "ondragmove",
      "ondrop",
      "oninput",
      "onkeydown",
      "onkeyup",
      "onkillfocus",
      "onlbuttondown",
      "onlbuttonup",
      "onmousedown",
      "onmouseenter",
      "onmouseleave",
      "onmousemove",
      "onmouseup",
      "onmousewheel",
      "onmove",
      "onrbuttondown",
      "onrbuttonup",
      "onsetfocus",
      "onsize",
      "ontouchend",
      "ontouchmove",
      "ontouchstart"
    ],
    "filename": "ImageControl.info"
  },
  {
    "componentname": "InnerdataChangedEventInfo",
    "events": [],
    "filename": "InnerdataChangedEventInfo.info"
  },
  {
    "componentname": "InputEventInfo",
    "events": [],
    "filename": "InputEventInfo.info"
  },
  {
    "componentname": "ItemChangeEventInfo",
    "events": [],
    "filename": "ItemChangeEventInfo.info"
  },
  {
    "componentname": "ItemClickEventInfo",
    "events": [],
    "filename": "ItemClickEventInfo.info"
  },
  {
    "componentname": "IconTextControl",
    "events": [
      "onclick",
      "oncontextmenu",
      "ondblclick",
      "ondrag",
      "ondragenter",
      "ondragleave",
      "ondragmove",
      "ondrop",
      "oninput",
      "onkeydown",
      "onkeyup",
      "onkillfocus",
      "onlbuttondown",
      "onlbuttonup",
      "onmousedown",
      "onmouseenter",
      "onmouseleave",
      "onmousemove",
      "onmouseup",
      "onmousewheel",
      "onmove",
      "onrbuttondown",
      "onrbuttonup",
      "onsetfocus",
      "onsize",
      "ontouchend",
      "ontouchmove",
      "ontouchstart"
    ],
    "filename": "IconTextControl.info"
  },
  {
    "componentname": "KillFocusEventInfo",
    "events": [],
    "filename": "KillFocusEventInfo.info"
  },
  {
    "componentname": "ImageViewer",
    "events": [
      "onclick",
      "oncontextmenu",
      "ondblclick",
      "ondevicebuttonup",
      "ondrag",
      "ondragenter",
      "ondragleave",
      "ondragmove",
      "ondrop",
      "oninput",
      "onkeydown",
      "onkeyup",
      "onkillfocus",
      "onlbuttondown",
      "onlbuttonup",
      "onload",
      "onmousedown",
      "onmouseenter",
      "onmouseleave",
      "onmousemove",
      "onmouseup",
      "onmousewheel",
      "onmove",
      "onrbuttondown",
      "onrbuttonup",
      "onsetfocus",
      "onsize",
      "ontouchend",
      "ontouchmove",
      "ontouchstart"
    ],
    "filename": "ImageViewer.info"
  },
  {
    "componentname": "KeyEventInfo",
    "events": [],
    "filename": "KeyEventInfo.info"
  },
  {
    "componentname": "LoadEventInfo",
    "events": [],
    "filename": "LoadEventInfo.info"
  },
  {
    "componentname": "LayoutChangeEventInfo",
    "events": [],
    "filename": "LayoutChangeEventInfo.info"
  },
  {
    "componentname": "ListBoxItemControl",
    "events": [
      "onclick",
      "oncontextmenu",
      "ondblclick",
      "ondrag",
      "ondragenter",
      "ondragleave",
      "ondragmove",
      "ondrop",
      "oninput",
      "onkeydown",
      "onkeyup",
      "onkillfocus",
      "onlbuttondown",
      "onlbuttonup",
      "onmousedown",
      "onmouseenter",
      "onmouseleave",
      "onmousemove",
      "onmouseup",
      "onmousewheel",
      "onmove",
      "onrbuttondown",
      "onrbuttonup",
      "onsetfocus",
      "onsize",
      "ontouchend",
      "ontouchmove",
      "ontouchstart"
    ],
    "filename": "ListBoxItemControl.info"
  },
  {
    "componentname": "Layout",
    "events": [],
    "filename": "Layout.info"
  },
  {
    "componentname": "ListBox",
    "events": [
      "canitemchange",
      "onclick",
      "oncontextmenu",
      "ondblclick",
      "ondevicebuttonup",
      "ondrag",
      "ondragenter",
      "ondragleave",
      "ondragmove",
      "ondrop",
      "onhscroll",
      "oninnerdatachanged",
      "oninput",
      "onitemchanged",
      "onitemclick",
      "onitemdblclick",
      "onkeydown",
      "onkeyup",
      "onkillfocus",
      "onlbuttondown",
      "onlbuttonup",
      "onmousedown",
      "onmouseenter",
      "onmouseleave",
      "onmousemove",
      "onmouseup",
      "onmousewheel",
      "onmove",
      "onrbuttondown",
      "onrbuttonup",
      "onsetfocus",
      "onsize",
      "ontouchend",
      "ontouchmove",
      "ontouchstart",
      "onvscroll"
    ],
    "filename": "ListBox.info"
  },
  {
    "componentname": "MenuClickEventInfo",
    "events": [],
    "filename": "MenuClickEventInfo.info"
  },
  {
    "componentname": "Menu",
    "events": [
      "onclick",
      "oncontextmenu",
      "ondblclick",
      "ondevicebuttonup",
      "ondrag",
      "ondragenter",
      "ondragleave",
      "ondragmove",
      "ondrop",
      "oninnerdatachanged",
      "oninput",
      "onkeydown",
      "onkeyup",
      "onkillfocus",
      "onlbuttondown",
      "onlbuttonup",
      "onmenuclick",
      "onmousedown",
      "onmouseenter",
      "onmouseleave",
      "onmousemove",
      "onmouseup",
      "onmousewheel",
      "onmove",
      "onrbuttondown",
      "onrbuttonup",
      "onsetfocus",
      "onsize",
      "ontouchend",
      "ontouchmove",
      "ontouchstart"
    ],
    "filename": "Menu.info"
  },
  {
    "componentname": "MenuContextMenuEventInfo",
    "events": [],
    "filename": "MenuContextMenuEventInfo.info"
  },
  {
    "componentname": "MainFrame",
    "events": [
      "onactivate",
      "onbeforeclose",
      "onclick",
      "onclose",
      "oncontextmenu",
      "ondblclick",
      "ondeactivate",
      "ondrag",
      "ondragenter",
      "ondragleave",
      "ondragmove",
      "ondrop",
      "oninput",
      "onkeydown",
      "onkeyup",
      "onkillfocus",
      "onlbuttondown",
      "onlbuttonup",
      "onmousedown",
      "onmouseenter",
      "onmouseleave",
      "onmousemove",
      "onmouseup",
      "onmousewheel",
      "onmove",
      "onorientationchange",
      "onrootcssclasschange",
      "onrbuttondown",
      "onrbuttonup",
      "onsetfocus",
      "onsize",
      "onsyscommand",
      "ontouchend",
      "ontouchmove",
      "ontouchstart"
    ],
    "filename": "MainFrame.info"
  },
  {
    "componentname": "MouseEventInfo",
    "events": [],
    "filename": "MouseEventInfo.info"
  },
  {
    "componentname": "MenuDragEventInfo",
    "events": [],
    "filename": "MenuDragEventInfo.info"
  },
  {
    "componentname": "MenuMouseEventInfo",
    "events": [],
    "filename": "MenuMouseEventInfo.info"
  },
  {
    "componentname": "MaskEdit",
    "events": [
      "canchange",
      "onchanged",
      "onclick",
      "oncontextmenu",
      "ondblclick",
      "ondevicebuttonup",
      "ondrag",
      "ondragenter",
      "ondragleave",
      "ondragmove",
      "ondrop",
      "oneditclick",
      "onimeaction",
      "oninput",
      "onkeydown",
      "onkeyup",
      "onkillfocus",
      "onlbuttondown",
      "onlbuttonup",
      "onmousedown",
      "onmouseenter",
      "onmouseleave",
      "onmousemove",
      "onmouseup",
      "onmousewheel",
      "onmove",
      "onrbuttondown",
      "onrbuttonup",
      "onsetfocus",
      "onsize",
      "ontouchend",
      "ontouchmove",
      "ontouchstart"
    ],
    "filename": "MaskEdit.info"
  },
  {
    "componentname": "MouseWheelEventInfo",
    "events": [],
    "filename": "MouseWheelEventInfo.info"
  },
  {
    "componentname": "MoveEventInfo",
    "events": [],
    "filename": "MoveEventInfo.info"
  },
  {
    "componentname": "MenuItemControl",
    "events": [
      "onclick",
      "oncontextmenu",
      "ondblclick",
      "ondrag",
      "ondragenter",
      "ondragleave",
      "ondragmove",
      "ondrop",
      "oninput",
      "onkeydown",
      "onkeyup",
      "onkillfocus",
      "onlbuttondown",
      "onlbuttonup",
      "onmouseenter",
      "onmouseleave",
      "onmousemove",
      "onmouseup",
      "onmousewheel",
      "onmove",
      "onrbuttondown",
      "onrbuttonup",
      "onsetfocus",
      "onsize",
      "ontouchend",
      "ontouchmove",
      "ontouchstart"
    ],
    "filename": "MenuItemControl.info"
  },
  {
    "componentname": "MultiComboListControl",
    "events": [
      "onclick",
      "oncontextmenu",
      "ondblclick",
      "ondrag",
      "ondragenter",
      "ondragleave",
      "ondragmove",
      "ondrop",
      "oninput",
      "onkeydown",
      "onkeyup",
      "onkillfocus",
      "onlbuttondown",
      "onlbuttonup",
      "onmousedown",
      "onmouseenter",
      "onmouseleave",
      "onmousemove",
      "onmouseup",
      "onmousewheel",
      "onmove",
      "onrbuttondown",
      "onrbuttonup",
      "onsetfocus",
      "onsize",
      "ontouchend",
      "ontouchmove",
      "ontouchstart"
    ],
    "filename": "MultiComboListControl.info"
  },
  {
    "componentname": "MultiComboTagBoxControl",
    "events": [
      "onclick",
      "oncontextmenu",
      "ondblclick",
      "ondrag",
      "ondragenter",
      "ondragleave",
      "ondragmove",
      "ondrop",
      "oninput",
      "onkeydown",
      "onkeyup",
      "onkillfocus",
      "onlbuttondown",
      "onlbuttonup",
      "onmousedown",
      "onmouseenter",
      "onmouseleave",
      "onmousemove",
      "onmouseup",
      "onmousewheel",
      "onmove",
      "onrbuttondown",
      "onrbuttonup",
      "onsetfocus",
      "onsize",
      "ontouchend",
      "ontouchmove",
      "ontouchstart"
    ],
    "filename": "MultiComboTagBoxControl.info"
  },
  {
    "componentname": "MultiLineTextFieldBoxControl",
    "events": [
      "onclick",
      "oncontextmenu",
      "ondblclick",
      "ondrag",
      "ondragenter",
      "ondragleave",
      "ondragmove",
      "ondrop",
      "oninput",
      "onkeydown",
      "onkeyup",
      "onkillfocus",
      "onlbuttondown",
      "onlbuttonup",
      "onmousedown",
      "onmouseenter",
      "onmouseleave",
      "onmousemove",
      "onmouseup",
      "onmousewheel",
      "onmove",
      "onrbuttondown",
      "onrbuttonup",
      "onsetfocus",
      "onsize",
      "ontouchend",
      "ontouchmove",
      "ontouchstart"
    ],
    "filename": "MultiLineTextFieldBoxControl.info"
  },
  {
    "componentname": "PageChangeEventInfo",
    "events": [],
    "filename": "PageChangeEventInfo.info"
  },
  {
    "componentname": "OrientationChangeEventInfo",
    "events": [],
    "filename": "OrientationChangeEventInfo.info"
  },
  {
    "componentname": "MultiLineTextField",
    "events": [
      "canchange",
      "onchanged",
      "onclick",
      "oncontextmenu",
      "ondblclick",
      "ondevicebuttonup",
      "ondrag",
      "ondragenter",
      "ondragleave",
      "ondragmove",
      "ondrop",
      "oneditclick",
      "onhscroll",
      "oninput",
      "onkeydown",
      "onkeyup",
      "onkillfocus",
      "onlbuttondown",
      "onlbuttonup",
      "onmousedown",
      "onmouseenter",
      "onmouseleave",
      "onmousemove",
      "onmouseup",
      "onmousewheel",
      "onmove",
      "onrbuttondown",
      "onrbuttonup",
      "onsetfocus",
      "onsize",
      "ontouchend",
      "ontouchmove",
      "ontouchstart",
      "onvscroll"
    ],
    "filename": "MultiLineTextField.info"
  },
  {
    "componentname": "PanelItem",
    "events": [],
    "filename": "PanelItem.info"
  },
  {
    "componentname": "MultiCombo",
    "events": [
      "canitemchange",
      "onclick",
      "oncloseup",
      "oncontextmenu",
      "ondblclick",
      "ondevicebuttonup",
      "ondrag",
      "ondragenter",
      "ondragleave",
      "ondragmove",
      "ondrop",
      "ondropdown",
      "oneditclick",
      "oninnerdatachanged",
      "oninput",
      "onitemchanged",
      "onitemclick",
      "onkeydown",
      "onkeyup",
      "onkillfocus",
      "onlbuttondown",
      "onlbuttonup",
      "onmousedown",
      "onmouseenter",
      "onmouseleave",
      "onmousemove",
      "onmouseup",
      "onmousewheel",
      "onmove",
      "onrbuttondown",
      "onrbuttonup",
      "onsetfocus",
      "onsize",
      "ontouchend",
      "ontouchmove",
      "ontouchstart"
    ],
    "filename": "MultiCombo.info"
  },
  {
    "componentname": "PickerHeadLineControl",
    "events": [
      "onclick",
      "oncontextmenu",
      "ondblclick",
      "ondrag",
      "ondragenter",
      "ondragleave",
      "ondragmove",
      "ondrop",
      "oninput",
      "onkeydown",
      "onkeyup",
      "onkillfocus",
      "onlbuttondown",
      "onlbuttonup",
      "onmousedown",
      "onmouseenter",
      "onmouseleave",
      "onmousemove",
      "onmouseup",
      "onmousewheel",
      "onmove",
      "onrbuttondown",
      "onrbuttonup",
      "onsetfocus",
      "onsize",
      "ontouchend",
      "ontouchmove",
      "ontouchstart"
    ],
    "filename": "PickerHeadLineControl.info"
  },
  {
    "componentname": "Paginator",
    "events": [
      "onclick",
      "oncontextmenu",
      "ondblclick",
      "ondevicePaginatorup",
      "ondrag",
      "ondragenter",
      "ondragleave",
      "ondragmove",
      "ondrop",
      "oninput",
      "onkeydown",
      "onkeyup",
      "onkillfocus",
      "onlbuttondown",
      "onlbuttonup",
      "onmousedown",
      "onmouseenter",
      "onmouseleave",
      "onmousemove",
      "onmouseup",
      "onmousewheel",
      "onmove",
      "onrbuttondown",
      "onrbuttonup",
      "onsetfocus",
      "onsize",
      "ontouchend",
      "ontouchmove",
      "ontouchstart",
      "onpagechanged"
    ],
    "filename": "Paginator.info"
  },
  {
    "componentname": "Panel",
    "events": [
      "onclick",
      "oncontextmenu",
      "ondblclick",
      "ondrag",
      "ondragenter",
      "ondragleave",
      "ondragmove",
      "ondrop",
      "oninput",
      "onkeydown",
      "onkeyup",
      "onkillfocus",
      "onlbuttondown",
      "onlbuttonup",
      "onmousedown",
      "onmouseenter",
      "onmouseleave",
      "onmousemove",
      "onmouseup",
      "onmousewheel",
      "onmove",
      "onrbuttondown",
      "onrbuttonup",
      "onsetfocus",
      "onsize",
      "ontouchend",
      "ontouchmove",
      "ontouchstart"
    ],
    "filename": "Panel.info"
  },
  {
    "componentname": "PopupDateRangePicker",
    "events": [
      "onchanged",
      "onclick",
      "oncloseup",
      "oncontextmenu",
      "ondayclick",
      "ondblclick",
      "ondevicebuttonup",
      "ondrag",
      "ondragenter",
      "ondragleave",
      "ondragmove",
      "ondrop",
      "oninnerdatachanged",
      "oninput",
      "onkeydown",
      "onkeyup",
      "onkillfocus",
      "onlbuttondown",
      "onlbuttonup",
      "onmousedown",
      "onmouseenter",
      "onmouseleave",
      "onmousemove",
      "onmouseup",
      "onmousewheel",
      "onmove",
      "onpopup",
      "onrbuttondown",
      "onrbuttonup",
      "onsetfocus",
      "onsize",
      "ontouchend",
      "ontouchmove",
      "ontouchstart"
    ],
    "filename": "PopupDateRangePicker.info"
  },
  {
    "componentname": "Plugin",
    "events": [
      "onclick",
      "oncontextmenu",
      "ondblclick",
      "ondrag",
      "ondragenter",
      "ondragleave",
      "ondragmove",
      "ondrop",
      "oninput",
      "onkeydown",
      "onkeyup",
      "onkillfocus",
      "onlbuttondown",
      "onlbuttonup",
      "onmousedown",
      "onmouseenter",
      "onmouseleave",
      "onmousemove",
      "onmouseup",
      "onmousewheel",
      "onmove",
      "onrbuttondown",
      "onrbuttonup",
      "onsetfocus",
      "onsize",
      "ontouchend",
      "ontouchmove",
      "ontouchstart"
    ],
    "filename": "Plugin.info"
  },
  {
    "componentname": "PopupMenu",
    "events": [
      "onclick",
      "oncloseup",
      "oncontextmenu",
      "ondblclick",
      "ondrag",
      "ondragenter",
      "ondragleave",
      "ondragmove",
      "ondrop",
      "oninnerdatachanged",
      "oninput",
      "onkeydown",
      "onkeyup",
      "onkillfocus",
      "onlbuttondown",
      "onlbuttonup",
      "onmenuclick",
      "onmousedown",
      "onmouseenter",
      "onmouseleave",
      "onmousemove",
      "onmouseup",
      "onmousewheel",
      "onmove",
      "onpopup",
      "onrbuttondown",
      "onrbuttonup",
      "onsetfocus",
      "onsize",
      "ontouchend",
      "ontouchmove",
      "ontouchstart"
    ],
    "filename": "PopupMenu.info"
  },
  {
    "componentname": "PopupMenuItemControl",
    "events": [
      "onclick",
      "oncontextmenu",
      "ondblclick",
      "ondrag",
      "ondragenter",
      "ondragleave",
      "ondragmove",
      "ondrop",
      "oninput",
      "onkeydown",
      "onkeyup",
      "onkillfocus",
      "onlbuttondown",
      "onlbuttonup",
      "onmouseenter",
      "onmouseleave",
      "onmousemove",
      "onmouseup",
      "onmousewheel",
      "onmove",
      "onrbuttondown",
      "onrbuttonup",
      "onsetfocus",
      "onsize",
      "ontouchend",
      "ontouchmove",
      "ontouchstart"
    ],
    "filename": "PopupMenuItemControl.info"
  },
  {
    "componentname": "PopupDiv",
    "events": [
      "onclick",
      "oncloseup",
      "oncontextmenu",
      "ondblclick",
      "ondevicebuttonup",
      "ondrag",
      "ondragenter",
      "ondragleave",
      "ondragmove",
      "ondrop",
      "onhscroll",
      "oninput",
      "onkeydown",
      "onkeyup",
      "onkillfocus",
      "onlbuttondown",
      "onlbuttonup",
      "onmousedown",
      "onmouseenter",
      "onmouseleave",
      "onmousemove",
      "onmouseup",
      "onmousewheel",
      "onmove",
      "onpopup",
      "onrbuttondown",
      "onrbuttonup",
      "onsetfocus",
      "onsize",
      "ontouchend",
      "ontouchmove",
      "ontouchstart",
      "onvscroll"
    ],
    "filename": "PopupDiv.info"
  },
  {
    "componentname": "RangeDateChangedEventInfo",
    "events": [],
    "filename": "RangeDateChangedEventInfo.info"
  },
  {
    "componentname": "ResizerControl",
    "events": [],
    "filename": "ResizerControl.info"
  },
  {
    "componentname": "ProgressBar",
    "events": [
      "onclick",
      "oncontextmenu",
      "ondblclick",
      "ondevicebuttonup",
      "ondrag",
      "ondragenter",
      "ondragleave",
      "ondragmove",
      "ondrop",
      "oninput",
      "onkeydown",
      "onkeyup",
      "onkillfocus",
      "onlbuttondown",
      "onlbuttonup",
      "onmousedown",
      "onmouseenter",
      "onmouseleave",
      "onmousemove",
      "onmouseup",
      "onmousewheel",
      "onmove",
      "onrbuttondown",
      "onrbuttonup",
      "onsetfocus",
      "onsize",
      "ontouchend",
      "ontouchmove",
      "ontouchstart"
    ],
    "filename": "ProgressBar.info"
  },
  {
    "componentname": "ResizerGhostControl",
    "events": [],
    "filename": "ResizerGhostControl.info"
  },
  {
    "componentname": "Radio",
    "events": [
      "canitemchange",
      "onclick",
      "oncontextmenu",
      "ondblclick",
      "ondevicebuttonup",
      "ondrag",
      "ondragenter",
      "ondragleave",
      "ondragmove",
      "ondrop",
      "oninnerdatachanged",
      "oninput",
      "onitemchanged",
      "onitemclick",
      "onkeydown",
      "onkeyup",
      "onkillfocus",
      "onlbuttondown",
      "onlbuttonup",
      "onmousedown",
      "onmouseenter",
      "onmouseleave",
      "onmousemove",
      "onmouseup",
      "onmousewheel",
      "onmove",
      "onrbuttondown",
      "onrbuttonup",
      "onsetfocus",
      "onsize",
      "ontouchend",
      "ontouchmove",
      "ontouchstart"
    ],
    "filename": "Radio.info"
  },
  {
    "componentname": "RadioItemControl",
    "events": [
      "onclick",
      "oncontextmenu",
      "ondblclick",
      "ondrag",
      "ondragenter",
      "ondragleave",
      "ondragmove",
      "ondrop",
      "oninput",
      "onkeydown",
      "onkeyup",
      "onkillfocus",
      "onlbuttondown",
      "onlbuttonup",
      "onmousedown",
      "onmouseenter",
      "onmouseleave",
      "onmousemove",
      "onmouseup",
      "onmousewheel",
      "onmove",
      "onrbuttondown",
      "onrbuttonup",
      "onsetfocus",
      "onsize",
      "ontouchend",
      "ontouchmove",
      "ontouchstart"
    ],
    "filename": "RadioItemControl.info"
  },
  {
    "componentname": "RootCssClassChangeEventInfo",
    "events": [],
    "filename": "RootCssClassChangeEventInfo.info"
  },
  {
    "componentname": "RowGroupExpandButtonControl",
    "events": [
      "onclick",
      "oncontextmenu",
      "ondblclick",
      "ondrag",
      "ondragenter",
      "ondragleave",
      "ondragmove",
      "ondrop",
      "oninput",
      "onkeydown",
      "onkeyup",
      "onkillfocus",
      "onlbuttondown",
      "onlbuttonup",
      "onmousedown",
      "onmouseenter",
      "onmouseleave",
      "onmousemove",
      "onmouseup",
      "onmousewheel",
      "onmove",
      "onrbuttondown",
      "onrbuttonup",
      "onsetfocus",
      "onsize",
      "ontouchend",
      "ontouchmove",
      "ontouchstart"
    ],
    "filename": "RowGroupExpandButtonControl.info"
  },
  {
    "componentname": "ScrollEventInfo",
    "events": [],
    "filename": "ScrollEventInfo.info"
  },
  {
    "componentname": "ScrollBarControl",
    "events": [],
    "filename": "ScrollBarControl.info"
  },
  {
    "componentname": "SizeEventInfo",
    "events": [],
    "filename": "SizeEventInfo.info"
  },
  {
    "componentname": "SetFocusEventInfo",
    "events": [],
    "filename": "SetFocusEventInfo.info"
  },
  {
    "componentname": "ScrollIndicatorControl",
    "events": [],
    "filename": "ScrollIndicatorControl.info"
  },
  {
    "componentname": "SketchLoadEventInfo",
    "events": [],
    "filename": "SketchLoadEventInfo.info"
  },
  {
    "componentname": "SketchErrorEventInfo",
    "events": [],
    "filename": "SketchErrorEventInfo.info"
  },
  {
    "componentname": "SketchEventInfo",
    "events": [],
    "filename": "SketchEventInfo.info"
  },
  {
    "componentname": "SpinBarControl",
    "events": [],
    "filename": "SpinBarControl.info"
  },
  {
    "componentname": "SplitterControl",
    "events": [],
    "filename": "SplitterControl.info"
  },
  {
    "componentname": "SpinEventInfo",
    "events": [],
    "filename": "SpinEventInfo.info"
  },
  {
    "componentname": "Sketch",
    "events": [
      "onclick",
      "oncontextmenu",
      "ondblclick",
      "ondevicebuttonup",
      "ondrag",
      "ondragenter",
      "ondragleave",
      "ondragmove",
      "ondrop",
      "onerror",
      "oninput",
      "onkeydown",
      "onkeyup",
      "onkillfocus",
      "onlbuttondown",
      "onlbuttonup",
      "onload",
      "onmousedown",
      "onmouseenter",
      "onmouseleave",
      "onmousemove",
      "onmouseup",
      "onmousewheel",
      "onmove",
      "onrbuttondown",
      "onrbuttonup",
      "onsetfocus",
      "onsize",
      "onsuccess",
      "ontouchend",
      "ontouchmove",
      "ontouchstart"
    ],
    "filename": "Sketch.info"
  },
  {
    "componentname": "StatusBarControl",
    "events": [],
    "filename": "StatusBarControl.info"
  },
  {
    "componentname": "Spin",
    "events": [
      "canchange",
      "onchanged",
      "onclick",
      "oncontextmenu",
      "ondblclick",
      "ondevicebuttonup",
      "ondrag",
      "ondragenter",
      "ondragleave",
      "ondragmove",
      "ondrop",
      "oneditclick",
      "oninput",
      "onkeydown",
      "onkeyup",
      "onkillfocus",
      "onlbuttondown",
      "onlbuttonup",
      "onmousedown",
      "onmouseenter",
      "onmouseleave",
      "onmousemove",
      "onmouseup",
      "onmousewheel",
      "onmove",
      "onrbuttondown",
      "onrbuttonup",
      "onsetfocus",
      "onsize",
      "onspin",
      "ontouchend",
      "ontouchmove",
      "ontouchstart"
    ],
    "filename": "Spin.info"
  },
  {
    "componentname": "StepControl",
    "events": [],
    "filename": "StepControl.info"
  },
  {
    "componentname": "StepChangeEventInfo",
    "events": [],
    "filename": "StepChangeEventInfo.info"
  },
  {
    "componentname": "Static",
    "events": [
      "onclick",
      "oncontextmenu",
      "ondblclick",
      "ondrag",
      "ondragenter",
      "ondragleave",
      "ondragmove",
      "ondrop",
      "oninput",
      "onkeydown",
      "onkeyup",
      "onkillfocus",
      "onlbuttondown",
      "onlbuttonup",
      "onmousedown",
      "onmouseenter",
      "onmouseleave",
      "onmousemove",
      "onmouseup",
      "onmousewheel",
      "onmove",
      "onrbuttondown",
      "onrbuttonup",
      "onsetfocus",
      "onsize",
      "ontouchend",
      "ontouchmove",
      "ontouchstart"
    ],
    "filename": "Static.info"
  },
  {
    "componentname": "SpinnerControl",
    "events": [
      "onclick",
      "oncontextmenu",
      "ondblclick",
      "ondrag",
      "ondragenter",
      "ondragleave",
      "ondragmove",
      "ondrop",
      "oninput",
      "onkeydown",
      "onkeyup",
      "onkillfocus",
      "onlbuttondown",
      "onlbuttonup",
      "onmousedown",
      "onmouseenter",
      "onmouseleave",
      "onmousemove",
      "onmouseup",
      "onmousewheel",
      "onmove",
      "onrbuttondown",
      "onrbuttonup",
      "onsetfocus",
      "onsize",
      "ontouchend",
      "ontouchmove",
      "ontouchstart"
    ],
    "filename": "SpinnerControl.info"
  },
  {
    "componentname": "SysCommandEventInfo",
    "events": [],
    "filename": "SysCommandEventInfo.info"
  },
  {
    "componentname": "Switch",
    "events": [
      "canchange",
      "onchanged",
      "onclick",
      "oncontextmenu",
      "ondblclick",
      "ondevicebuttonup",
      "ondrag",
      "ondragenter",
      "ondragleave",
      "ondragmove",
      "ondrop",
      "oninput",
      "onkeydown",
      "onkeyup",
      "onkillfocus",
      "onlbuttondown",
      "onlbuttonup",
      "onmousedown",
      "onmouseenter",
      "onmouseleave",
      "onmousemove",
      "onmouseup",
      "onmousewheel",
      "onmove",
      "onrbuttondown",
      "onsetfocus",
      "onsize",
      "ontouchend",
      "ontouchmove",
      "ontouchstart"
    ],
    "filename": "Switch.info"
  },
  {
    "componentname": "TabBarButtonSetControl",
    "events": [],
    "filename": "TabBarButtonSetControl.info"
  },
  {
    "componentname": "SwitchButtonControl",
    "events": [
      "canchange",
      "onchanged",
      "onclick",
      "oncontextmenu",
      "ondblclick",
      "ondevicebuttonup",
      "ondrag",
      "ondragenter",
      "ondragleave",
      "ondragmove",
      "ondrop",
      "oninput",
      "onkeydown",
      "onkeyup",
      "onkillfocus",
      "onlbuttondown",
      "onlbuttonup",
      "onmousedown",
      "onmouseenter",
      "onmouseleave",
      "onmousemove",
      "onmouseup",
      "onmousewheel",
      "onmove",
      "onrbuttondown",
      "onsetfocus",
      "onsize",
      "ontouchend",
      "ontouchmove",
      "ontouchstart"
    ],
    "filename": "SwitchButtonControl.info"
  },
  {
    "componentname": "TabBarHeadButtonSetControl",
    "events": [],
    "filename": "TabBarHeadButtonSetControl.info"
  },
  {
    "componentname": "TabBarControl",
    "events": [],
    "filename": "TabBarControl.info"
  },
  {
    "componentname": "SwitchButtonItemControl",
    "events": [
      "canchange",
      "onchanged",
      "onclick",
      "oncontextmenu",
      "ondblclick",
      "ondevicebuttonup",
      "ondrag",
      "ondragenter",
      "ondragleave",
      "ondragmove",
      "ondrop",
      "oninput",
      "onkeydown",
      "onkeyup",
      "onkillfocus",
      "onlbuttondown",
      "onlbuttonup",
      "onmousedown",
      "onmouseenter",
      "onmouseleave",
      "onmousemove",
      "onmouseup",
      "onmousewheel",
      "onmove",
      "onrbuttondown",
      "onsetfocus",
      "onsize",
      "ontouchend",
      "ontouchmove",
      "ontouchstart"
    ],
    "filename": "SwitchButtonItemControl.info"
  },
  {
    "componentname": "TabBarItemControl",
    "events": [],
    "filename": "TabBarItemControl.info"
  },
  {
    "componentname": "TabBarItemSetControl",
    "events": [],
    "filename": "TabBarItemSetControl.info"
  },
  {
    "componentname": "Tab",
    "events": [
      "canchange",
      "onchanged",
      "onclick",
      "oncontextmenu",
      "ondblclick",
      "ondevicebuttonup",
      "ondrag",
      "ondragenter",
      "ondragleave",
      "ondragmove",
      "ondrop",
      "onextrabuttonclick",
      "oninput",
      "onkeydown",
      "onkeyup",
      "onkillfocus",
      "onlbuttondown",
      "onlbuttonup",
      "onmousedown",
      "onmouseenter",
      "onmouseleave",
      "onmousemove",
      "onmouseup",
      "onmousewheel",
      "onmove",
      "onrbuttondown",
      "onrbuttonup",
      "onsetfocus",
      "onsize",
      "ontouchend",
      "ontouchmove",
      "ontouchstart"
    ],
    "filename": "Tab.info"
  },
  {
    "componentname": "TabMouseEventInfo",
    "events": [],
    "filename": "TabMouseEventInfo.info"
  },
  {
    "componentname": "TabButtonIconControl",
    "events": [
      "onclick",
      "oncontextmenu",
      "ondblclick",
      "ondrag",
      "ondragenter",
      "ondragleave",
      "ondragmove",
      "ondrop",
      "oninput",
      "onkeydown",
      "onkeyup",
      "onkillfocus",
      "onlbuttondown",
      "onlbuttonup",
      "onmousedown",
      "onmouseenter",
      "onmouseleave",
      "onmousemove",
      "onmouseup",
      "onmousewheel",
      "onmove",
      "onrbuttondown",
      "onrbuttonup",
      "onsetfocus",
      "onsize",
      "ontouchend",
      "ontouchmove",
      "ontouchstart"
    ],
    "filename": "TabButtonIconControl.info"
  },
  {
    "componentname": "TabIndexChangeEventInfo",
    "events": [],
    "filename": "TabIndexChangeEventInfo.info"
  },
  {
    "componentname": "TabButtonItemControl",
    "events": [
      "onclick",
      "oncontextmenu",
      "ondblclick",
      "ondrag",
      "ondragenter",
      "ondragleave",
      "ondragmove",
      "ondrop",
      "oninput",
      "onkeydown",
      "onkeyup",
      "onkillfocus",
      "onlbuttondown",
      "onlbuttonup",
      "onmousedown",
      "onmouseenter",
      "onmouseleave",
      "onmousemove",
      "onmouseup",
      "onmousewheel",
      "onmove",
      "onrbuttondown",
      "onrbuttonup",
      "onsetfocus",
      "onsize",
      "ontouchend",
      "ontouchmove",
      "ontouchstart"
    ],
    "filename": "TabButtonItemControl.info"
  },
  {
    "componentname": "TabpageControl",
    "events": [
      "onclick",
      "oncontextmenu",
      "ondblclick",
      "ondevicebuttonup",
      "ondrag",
      "ondragenter",
      "ondragleave",
      "ondragmove",
      "ondrop",
      "onhscroll",
      "oninput",
      "onkeydown",
      "onkeyup",
      "onkillfocus",
      "onlbuttondown",
      "onlbuttonup",
      "onmousedown",
      "onmouseenter",
      "onmouseleave",
      "onmousemove",
      "onmouseup",
      "onmousewheel",
      "onmove",
      "onrbuttondown",
      "onrbuttonup",
      "onsetfocus",
      "onsize",
      "ontouchend",
      "ontouchmove",
      "ontouchstart",
      "onvscroll"
    ],
    "filename": "TabpageControl.info"
  },
  {
    "componentname": "TagBoxControl",
    "events": [
      "onclick",
      "oncontextmenu",
      "ondblclick",
      "ondrag",
      "ondragenter",
      "ondragleave",
      "ondragmove",
      "ondrop",
      "oninput",
      "onkeydown",
      "onkeyup",
      "onkillfocus",
      "onlbuttondown",
      "onlbuttonup",
      "onmousedown",
      "onmouseenter",
      "onmouseleave",
      "onmousemove",
      "onmouseup",
      "onmousewheel",
      "onmove",
      "onrbuttondown",
      "onrbuttonup",
      "onsetfocus",
      "onsize",
      "ontouchend",
      "ontouchmove",
      "ontouchstart"
    ],
    "filename": "TagBoxControl.info"
  },
  {
    "componentname": "TextFieldBoxControl",
    "events": [
      "onclick",
      "oncontextmenu",
      "ondblclick",
      "ondrag",
      "ondragenter",
      "ondragleave",
      "ondragmove",
      "ondrop",
      "oninput",
      "onkeydown",
      "onkeyup",
      "onkillfocus",
      "onlbuttondown",
      "onlbuttonup",
      "onmousedown",
      "onmouseenter",
      "onmouseleave",
      "onmousemove",
      "onmouseup",
      "onmousewheel",
      "onmove",
      "onrbuttondown",
      "onrbuttonup",
      "onsetfocus",
      "onsize",
      "ontouchend",
      "ontouchmove",
      "ontouchstart"
    ],
    "filename": "TextFieldBoxControl.info"
  },
  {
    "componentname": "TextArea",
    "events": [
      "canchange",
      "onchanged",
      "onclick",
      "oncontextmenu",
      "ondblclick",
      "ondevicebuttonup",
      "ondrag",
      "ondragenter",
      "ondragleave",
      "ondragmove",
      "ondrop",
      "oneditclick",
      "onhscroll",
      "oninput",
      "onkeydown",
      "onkeyup",
      "onkillfocus",
      "onlbuttondown",
      "onlbuttonup",
      "onmousedown",
      "onmouseenter",
      "onmouseleave",
      "onmousemove",
      "onmouseup",
      "onmousewheel",
      "onmove",
      "onrbuttondown",
      "onrbuttonup",
      "onsetfocus",
      "onsize",
      "ontouchend",
      "ontouchmove",
      "ontouchstart",
      "onvscroll"
    ],
    "filename": "TextArea.info"
  },
  {
    "componentname": "TextField",
    "events": [
      "canchange",
      "onchanged",
      "onclick",
      "oncontextmenu",
      "ondblclick",
      "ondevicebuttonup",
      "ondrag",
      "ondragenter",
      "ondragleave",
      "ondragmove",
      "ondrop",
      "oneditclick",
      "oninput",
      "oninvalid",
      "onkeydown",
      "onkeyup",
      "onkillfocus",
      "onlbuttondown",
      "onlbuttonup",
      "onleadingbuttonclick",
      "onmousedown",
      "onmouseenter",
      "onmouseleave",
      "onmousemove",
      "onmouseup",
      "onmousewheel",
      "onmove",
      "onrbuttondown",
      "onrbuttonup",
      "onsetfocus",
      "onsize",
      "ontouchend",
      "ontouchmove",
      "ontouchstart",
      "ontrailingbuttonclick"
    ],
    "filename": "TextField.info"
  },
  {
    "componentname": "TimePickerControl",
    "events": [
      "onclick",
      "oncontextmenu",
      "ondblclick",
      "ondrag",
      "ondragenter",
      "ondragleave",
      "ondragmove",
      "ondrop",
      "oninput",
      "onkeydown",
      "onkeyup",
      "onkillfocus",
      "onlbuttondown",
      "onlbuttonup",
      "onmousedown",
      "onmouseenter",
      "onmouseleave",
      "onmousemove",
      "onmouseup",
      "onmousewheel",
      "onmove",
      "onrbuttondown",
      "onrbuttonup",
      "onsetfocus",
      "onsize",
      "ontouchend",
      "ontouchmove",
      "ontouchstart"
    ],
    "filename": "TimePickerControl.info"
  },
  {
    "componentname": "TileFrameSet",
    "events": [
      "onactivate",
      "onbeforeclose",
      "onclick",
      "onclose",
      "oncontextmenu",
      "ondblclick",
      "ondeactivate",
      "ondrag",
      "ondragenter",
      "ondragleave",
      "ondragmove",
      "ondrop",
      "oninput",
      "onkeydown",
      "onkeyup",
      "onkillfocus",
      "onlbuttondown",
      "onlbuttonup",
      "onmousedown",
      "onmouseenter",
      "onmouseleave",
      "onmousemove",
      "onmouseup",
      "onmousewheel",
      "onmove",
      "onorientationchange",
      "onrootcssclasschange",
      "onrbuttondown",
      "onrbuttonup",
      "onsetfocus",
      "onsize",
      "onsyscommand",
      "ontouchend",
      "ontouchmove",
      "ontouchstart"
    ],
    "filename": "TileFrameSet.info"
  },
  {
    "componentname": "TimePickerGroupControl",
    "events": [
      "onclick",
      "oncontextmenu",
      "ondblclick",
      "ondrag",
      "ondragenter",
      "ondragleave",
      "ondragmove",
      "ondrop",
      "oninput",
      "onkeydown",
      "onkeyup",
      "onkillfocus",
      "onlbuttondown",
      "onlbuttonup",
      "onmousedown",
      "onmouseenter",
      "onmouseleave",
      "onmousemove",
      "onmouseup",
      "onmousewheel",
      "onmove",
      "onrbuttondown",
      "onrbuttonup",
      "onsetfocus",
      "onsize",
      "ontouchend",
      "ontouchmove",
      "ontouchstart"
    ],
    "filename": "TimePickerGroupControl.info"
  },
  {
    "componentname": "TitleBarControl",
    "events": [],
    "filename": "TitleBarControl.info"
  },
  {
    "componentname": "TouchInputInfo",
    "events": [],
    "filename": "TouchInputInfo.info"
  },
  {
    "componentname": "TrayBalloonTipHideEventInfo",
    "events": [],
    "filename": "TrayBalloonTipHideEventInfo.info"
  },
  {
    "componentname": "ValueChangedEventInfo",
    "events": [],
    "filename": "ValueChangedEventInfo.info"
  },
  {
    "componentname": "TouchEventInfo",
    "events": [],
    "filename": "TouchEventInfo.info"
  },
  {
    "componentname": "TitleBarButtonControl",
    "events": [
      "onclick",
      "oncontextmenu",
      "ondblclick",
      "ondevicebuttonup",
      "ondrag",
      "ondragenter",
      "ondragleave",
      "ondragmove",
      "ondrop",
      "oninput",
      "onkeydown",
      "onkeyup",
      "onkillfocus",
      "onlbuttondown",
      "onlbuttonup",
      "onmousedown",
      "onmouseenter",
      "onmouseleave",
      "onmousemove",
      "onmouseup",
      "onmousewheel",
      "onmove",
      "onrbuttondown",
      "onrbuttonup",
      "onsetfocus",
      "onsize",
      "ontouchend",
      "ontouchmove",
      "ontouchstart"
    ],
    "filename": "TitleBarButtonControl.info"
  },
  {
    "componentname": "VideoCurrentTimeChangedEventInfo",
    "events": [],
    "filename": "VideoCurrentTimeChangedEventInfo.info"
  },
  {
    "componentname": "TitleBarIconTextControl",
    "events": [
      "onclick",
      "oncontextmenu",
      "ondblclick",
      "ondrag",
      "ondragenter",
      "ondragleave",
      "ondragmove",
      "ondrop",
      "oninput",
      "onkeydown",
      "onkeyup",
      "onkillfocus",
      "onlbuttondown",
      "onlbuttonup",
      "onmousedown",
      "onmouseenter",
      "onmouseleave",
      "onmousemove",
      "onmouseup",
      "onmousewheel",
      "onmove",
      "onrbuttondown",
      "onrbuttonup",
      "onsetfocus",
      "onsize",
      "ontouchend",
      "ontouchmove",
      "ontouchstart"
    ],
    "filename": "TitleBarIconTextControl.info"
  },
  {
    "componentname": "TreeItemIconControl",
    "events": [
      "onclick",
      "oncontextmenu",
      "ondblclick",
      "ondrag",
      "ondragenter",
      "ondragleave",
      "ondragmove",
      "ondrop",
      "oninput",
      "onkeydown",
      "onkeyup",
      "onkillfocus",
      "onlbuttondown",
      "onlbuttonup",
      "onmousedown",
      "onmouseenter",
      "onmouseleave",
      "onmousemove",
      "onmouseup",
      "onmousewheel",
      "onmove",
      "onrbuttondown",
      "onrbuttonup",
      "onsetfocus",
      "onsize",
      "ontouchend",
      "ontouchmove",
      "ontouchstart"
    ],
    "filename": "TreeItemIconControl.info"
  },
  {
    "componentname": "VFrameSet",
    "events": [
      "onactivate",
      "onbeforeclose",
      "onclick",
      "onclose",
      "oncontextmenu",
      "ondblclick",
      "ondeactivate",
      "ondrag",
      "ondragenter",
      "ondragleave",
      "ondragmove",
      "ondrop",
      "oninput",
      "onkeydown",
      "onkeyup",
      "onkillfocus",
      "onlbuttondown",
      "onlbuttonup",
      "onmousedown",
      "onmouseenter",
      "onmouseleave",
      "onmousemove",
      "onmouseup",
      "onmousewheel",
      "onmove",
      "onorientationchange",
      "onrootcssclasschange",
      "onrbuttondown",
      "onrbuttonup",
      "onsetfocus",
      "onsize",
      "onsyscommand",
      "ontouchend",
      "ontouchmove",
      "ontouchstart"
    ],
    "filename": "VFrameSet.info"
  },
  {
    "componentname": "VideoErrorEventInfo",
    "events": [],
    "filename": "VideoErrorEventInfo.info"
  },
  {
    "componentname": "VideoPlayStateChangedEventInfo",
    "events": [],
    "filename": "VideoPlayStateChangedEventInfo.info"
  },
  {
    "componentname": "VirtualFile",
    "events": [
      "onerror",
      "onsuccess"
    ],
    "filename": "VirtualFile.info"
  },
  {
    "componentname": "VirtualFileEventInfo",
    "events": [],
    "filename": "VirtualFileEventInfo.info"
  },
  {
    "componentname": "VirtualFileErrorEventInfo",
    "events": [],
    "filename": "VirtualFileErrorEventInfo.info"
  },
  {
    "componentname": "VideoPlayer",
    "events": [
      "onclick",
      "oncontextmenu",
      "oncurrenttimechanged",
      "ondblclick",
      "ondrag",
      "ondragenter",
      "ondragleave",
      "ondragmove",
      "ondrop",
      "onerror",
      "oninput",
      "onkeydown",
      "onkeyup",
      "onkillfocus",
      "onlbuttondown",
      "onlbuttonup",
      "onmousedown",
      "onmouseenter",
      "onmouseleave",
      "onmousemove",
      "onmouseup",
      "onmousewheel",
      "onmove",
      "onplaystatuschanged",
      "onrbuttondown",
      "onrbuttonup",
      "onsetfocus",
      "onsize",
      "ontouchend",
      "ontouchmove",
      "ontouchstart"
    ],
    "filename": "VideoPlayer.info"
  },
  {
    "componentname": "WebLoadCompEventInfo",
    "events": [],
    "filename": "WebLoadCompEventInfo.info"
  },
  {
    "componentname": "View",
    "events": [
      "onclick",
      "oncontextmenu",
      "ondblclick",
      "ondevicebuttonup",
      "ondrag",
      "ondragenter",
      "ondragleave",
      "ondragmove",
      "ondrop",
      "onhscroll",
      "oninput",
      "onkeydown",
      "onkeyup",
      "onkillfocus",
      "onlbuttondown",
      "onlbuttonup",
      "onmousedown",
      "onmouseenter",
      "onmouseleave",
      "onmousemove",
      "onmouseup",
      "onmousewheel",
      "onmove",
      "onrbuttondown",
      "onrbuttonup",
      "onsetfocus",
      "onsize",
      "ontouchend",
      "ontouchmove",
      "ontouchstart",
      "onvscroll"
    ],
    "filename": "View.info"
  },
  {
    "componentname": "WebUserNotifyEventInfo",
    "events": [],
    "filename": "WebUserNotifyEventInfo.info"
  },
  {
    "componentname": "WebBrowser",
    "events": [
      "onclick",
      "oncontextmenu",
      "ondblclick",
      "ondevicebuttonup",
      "ondrag",
      "ondragenter",
      "ondragleave",
      "ondragmove",
      "ondrop",
      "oninput",
      "onkeydown",
      "onkeyup",
      "onkillfocus",
      "onlbuttondown",
      "onlbuttonup",
      "onloadcompleted",
      "onmousedown",
      "onmouseenter",
      "onmouseleave",
      "onmousemove",
      "onmouseup",
      "onmousewheel",
      "onmove",
      "onrbuttondown",
      "onrbuttonup",
      "onsetfocus",
      "onsize",
      "ontouchend",
      "ontouchmove",
      "ontouchstart",
      "onusernotify"
    ],
    "filename": "WebBrowser.info"
  },
  {
    "componentname": "WebView",
    "events": [
      "onclick",
      "oncontextmenu",
      "ondblclick",
      "ondevicebuttonup",
      "ondrag",
      "ondragenter",
      "ondragleave",
      "ondragmove",
      "ondrop",
      "oninput",
      "onkeydown",
      "onkeyup",
      "onkillfocus",
      "onlbuttondown",
      "onlbuttonup",
      "onloadcompleted",
      "onmousedown",
      "onmouseenter",
      "onmouseleave",
      "onmousemove",
      "onmouseup",
      "onmousewheel",
      "onmove",
      "onrbuttondown",
      "onrbuttonup",
      "onsetfocus",
      "onsize",
      "ontouchend",
      "ontouchmove",
      "ontouchstart",
      "onusernotify"
    ],
    "filename": "WebView.info"
  }
]